odoo/addons/packaging_uom/README.rst
odoo/addons/packaging_uom/__init__.py
odoo/addons/packaging_uom/__manifest__.py
odoo/addons/packaging_uom/i18n/cs_CZ.po
odoo/addons/packaging_uom/i18n/de.po
odoo/addons/packaging_uom/i18n/es.po
odoo/addons/packaging_uom/i18n/fi.po
odoo/addons/packaging_uom/i18n/fr.po
odoo/addons/packaging_uom/i18n/hr.po
odoo/addons/packaging_uom/i18n/hr_HR.po
odoo/addons/packaging_uom/i18n/it.po
odoo/addons/packaging_uom/i18n/nl.po
odoo/addons/packaging_uom/i18n/packaging_uom.pot
odoo/addons/packaging_uom/i18n/pt.po
odoo/addons/packaging_uom/i18n/pt_BR.po
odoo/addons/packaging_uom/i18n/sl.po
odoo/addons/packaging_uom/models/__init__.py
odoo/addons/packaging_uom/models/product_packaging.py
odoo/addons/packaging_uom/static/description/icon.png
odoo/addons/packaging_uom/tests/__init__.py
odoo/addons/packaging_uom/tests/test_product_packaging.py
odoo/addons/packaging_uom/views/product_packaging_views.xml
odoo11_addon_packaging_uom-11.0.1.0.1.dist-info/METADATA
odoo11_addon_packaging_uom-11.0.1.0.1.dist-info/WHEEL
odoo11_addon_packaging_uom-11.0.1.0.1.dist-info/top_level.txt
odoo11_addon_packaging_uom-11.0.1.0.1.dist-info/RECORD
